<beans xmlns="http://www.springframework.org/schema/beans"
       xmlns:xsi="http://www.w3.org/2001/XMLSchema-instance"
       xmlns:tx="http://www.springframework.org/schema/tx"
       xmlns:mvc="http://www.springframework.org/schema/mvc"
       xmlns:context="http://www.springframework.org/schema/context"
       xmlns:task="http://www.springframework.org/schema/task"
       xsi:schemaLocation="http://www.springframework.org/schema/beans http://www.springframework.org/schema/beans/spring-beans-4.0.xsd
       http://www.springframework.org/schema/tx http://www.springframework.org/schema/tx/spring-tx.xsd
       http://www.springframework.org/schema/mvc http://www.springframework.org/schema/mvc/spring-mvc-4.0.xsd
       http://www.springframework.org/schema/context http://www.springframework.org/schema/context/spring-context-4.0.xsd
       http://www.springframework.org/schema/task http://www.springframework.org/schema/task/spring-task-4.0.xsd">

    <!-- Specifying base package of the Components like Controller, Service, DAO -->
    <context:component-scan base-package="kuidd.bot.commiton"/>
    <!-- Getting Database properties -->
    <!--<context:property-placeholder location="classpath*:/hibernate.properties"/>-->
    <context:property-placeholder location="classpath*:/config.properties"/>

    <mvc:annotation-driven />
    <!-- Specifying the Resource location to load JS, CSS, Images etc -->
    <mvc:resources mapping="/resources/**" location="/resources/" />

    <!-- View Resolver -->
    <bean class="org.springframework.web.servlet.view.InternalResourceViewResolver">
        <property name="viewClass" value="org.springframework.web.servlet.view.JstlView"/>
        <property name="prefix" value="/WEB-INF/pages/"/>
        <property name="suffix" value=".jsp"/>
    </bean>


    <!-- DataSource -->
    <bean id="dataSource" class="com.mchange.v2.c3p0.ComboPooledDataSource" destroy-method="close">
        <property name="driverClass" value="${datasource.driverClass}"/>
        <property name="jdbcUrl" value="${datasource.jdbcUrl}"/>
        <property name="user" value="${datasource.user}"/>
        <property name="password" value="${datasource.password}"/>

        <property name="acquireIncrement" value="${datasource.acquireIncrement}"/>
        <property name="minPoolSize" value="${datasource.minPoolSize}"/>
        <property name="maxPoolSize" value="${datasource.maxPoolSize}"/>
        <property name="maxIdleTime" value="${datasource.maxIdleTime}"/>
    </bean>

    <!-- Hibernate SessionFactory -->
    <bean id="sessionFactory" class="org.springframework.orm.hibernate4.LocalSessionFactoryBean">
        <property name="dataSource" ref="dataSource"/>
        <property name="hibernateProperties">
            <props>
                <prop key="hibernate.dialect">${hibernate.dialect}</prop>
                <prop key="hibernate.format_sql">${hibernate.format_sql}</prop>
                <prop key="hibernate.enable_lazy_load_no_trans">${hibernate.enable_lazy_load_no_trans}</prop>
                <prop key="hibernate.connection.characterEncoding">${hibernate.connection.characterEncoding}</prop>
            </props>
            </property>
        <property name="packagesToScan" value="kuidd.bot.commiton.entity"/>
    </bean>

    <!-- Transaction -->
    <bean id="transactionManager" class="org.springframework.orm.hibernate4.HibernateTransactionManager">
        <property name="sessionFactory" ref="sessionFactory"/>
    </bean>

    <tx:annotation-driven transaction-manager="transactionManager"/>

    <bean id="liquibase" class="liquibase.integration.spring.SpringLiquibase">
        <property name="dataSource" ref="dataSource" />
        <property name="changeLog" value="classpath:/version/db-changelog.xml" />
        <property name="contexts" value="test, production" />
    </bean>

    <!-- Scheduler -->
    <task:annotation-driven executor="executor" scheduler="scheduler"/>
    <task:executor id="executor" pool-size="5"/>
    <task:scheduler id="scheduler" pool-size="10"/>

</beans>